italian_translator/__init__.py
italian_translator/extract_examples.py
italian_translator/get_translations.py
italian_translator/main.py
italian_translator/show_examples.py
italian_translator/show_translations.py
italian_translator/urls.py
italian_translator-0.2.0.dist-info/LICENSE
italian_translator-0.2.0.dist-info/METADATA
italian_translator-0.2.0.dist-info/WHEEL
italian_translator-0.2.0.dist-info/entry_points.txt
italian_translator-0.2.0.dist-info/top_level.txt
italian_translator-0.2.0.dist-info/RECORD
