Metadata-Version: 2.1
Name: italian_translator
Version: 0.2.0
Summary: A command-line tool for translating Italian words using Reverso Context.
Home-page: https://github.com/seafoodd/italian_translator
Author: seafood
Author-email: mail.seafood@proton.me
Classifier: Programming Language :: Python :: 3
Classifier: License :: OSI Approved :: MIT License
Classifier: Operating System :: OS Independent
Requires-Python: >=3.6
License-File: LICENSE
Requires-Dist: requests
Requires-Dist: beautifulsoup4
Requires-Dist: colorama
